bqcloud/__init__.py
bqcloud/_version.py
bqcloud/abstract_result.py
bqcloud/annealing.py
bqcloud/api.py
bqcloud/data.py
bqcloud/datafactory.py
bqcloud/device.py
bqcloud/local.py
bqcloud/task.py
bqcloud/device_specific/__init__.py
bqcloud/device_specific/aws_device.py
blueqat_cloud-0.0.9.dist-info/METADATA
blueqat_cloud-0.0.9.dist-info/WHEEL
blueqat_cloud-0.0.9.dist-info/top_level.txt
blueqat_cloud-0.0.9.dist-info/RECORD
