Metadata-Version: 2.1
Name: blueqat-cloud
Version: 0.0.9
Summary: Blueqat cloud API
Author: gyu-don
Author-email: kato@blueqat.com
License: Apache-2.0
Platform: UNKNOWN
Classifier: Development Status :: 3 - Alpha
Classifier: License :: OSI Approved :: Apache Software License
Classifier: Programming Language :: Python :: 3.7
Classifier: Programming Language :: Python :: 3.8
Classifier: Programming Language :: Python :: 3.9
Classifier: Programming Language :: Python :: 3.10
Requires-Dist: blueqat (>=0.4.3)
Requires-Dist: braket-backend-blueqat (>=0.0.4)
Requires-Dist: amazon-braket-sdk (>=1.5.13)
Requires-Dist: pandas (>=1.2)
